distfuse/__init__.py
distfuse/distfuse.py
distfuse/version.py
distfuse-0.1.4.dist-info/LICENSE
distfuse-0.1.4.dist-info/METADATA
distfuse-0.1.4.dist-info/WHEEL
distfuse-0.1.4.dist-info/top_level.txt
distfuse-0.1.4.dist-info/RECORD
