Metadata-Version: 2.1
Name: distfuse
Version: 0.1.4
Summary: Compute DistFuse similarity scores from embedding models and APIs
Home-page: https://github.com/gentaiscool/distfuse
Author: Genta Indra Winata
Author-email: gentaindrawinata@gmail.com
License: Apache 2.0 License
Project-URL: Bug Tracker, https://github.com/gentaiscool/distfuse/issues
Classifier: Programming Language :: Python :: 3
Classifier: License :: OSI Approved :: MIT License
Classifier: Operating System :: OS Independent
Requires-Python: >=3.7
License-File: LICENSE
Requires-Dist: scikit-learn >=1.5.0
Requires-Dist: sentence-transformers
Requires-Dist: numpy
Requires-Dist: openai
Requires-Dist: cohere
